py_webrtcrnnvad-0.0.1.dist-info/top_level.txt
py_webrtcrnnvad-0.0.1.dist-info/WHEEL
py_webrtcrnnvad-0.0.1.dist-info/METADATA
py_webrtcrnnvad-0.0.1.dist-info/RECORD
py_webrtcrnnvad-0.0.1.dist-info/LICENSE
py_webrtcrnnvad/example.py
py_webrtcrnnvad/_py_webrtcrnnvad.pypy38-pp73-x86_64-linux-gnu.so
py_webrtcrnnvad/__init__.py
